et_engine_cli/__init__.py
et_engine_cli/main.py
et_engine_cli/batches/__init__.py
et_engine_cli/batches/commands.py
et_engine_cli/filesystems/__init__.py
et_engine_cli/filesystems/commands.py
et_engine_cli/tools/__init__.py
et_engine_cli/tools/commands.py
et_engine_cli/tools/templates/python_tool/Dockerfile
et_engine_cli/tools/templates/python_tool/README.md
et_engine_cli/tools/templates/python_tool/test.sh
et_engine_cli/tools/templates/python_tool/tool.json
et_engine_cli/tools/templates/python_tool/tool.py
et_engine_cli/tools/templates/python_tool/tool_name.py
et_engine_cli-0.0.1.dist-info/LICENSE
et_engine_cli-0.0.1.dist-info/METADATA
et_engine_cli-0.0.1.dist-info/WHEEL
et_engine_cli-0.0.1.dist-info/entry_points.txt
et_engine_cli-0.0.1.dist-info/top_level.txt
et_engine_cli-0.0.1.dist-info/RECORD
