Metadata-Version: 2.1
Name: et_engine_cli
Version: 0.0.1
Summary: Command Line Interface for the ET Engine
Author-email: "Exploration Technologies, Inc." <info@exploretech.ai>
License: 
Requires-Python: >=3.11.9
License-File: LICENSE
Requires-Dist: click>=8.1
Requires-Dist: docker
Requires-Dist: et_engine>=0.0.1
